{"type":"Topology","arcs":[[[2109,960],[55,-84],[-80,-143],[25,-79],[-32,-24],[-64,54],[-113,55],[-10,67],[18,66],[48,118],[62,-120],[52,-7],[-29,82],[7,27],[61,-12]],[[349,1277],[9,-29],[67,-68],[16,-51],[-5,-105],[-68,-10],[-103,129],[-27,-31],[10,-64],[-10,-60],[-40,-55],[-54,-22],[-58,18],[-48,57],[-38,142],[66,70],[-1,125],[115,115],[83,-15],[54,-42],[28,-60],[4,-44]],[[2523,1459],[31,-31],[6,-52],[-134,-196],[-33,9],[19,93],[-14,75],[-82,-48],[-21,36],[5,62],[33,52],[57,15],[87,-41],[46,26]],[[3601,1323],[-77,26],[-26,101],[17,92],[49,0],[131,-83],[-6,-49],[-33,-28],[-75,-6],[20,-53]],[[3229,1312],[90,-81],[-24,-39],[-57,-21],[-63,42],[11,88],[43,11]],[[3487,1704],[-103,-57],[-20,7],[0,75],[68,135],[51,1],[44,-55],[-18,-77],[-22,-29]],[[1095,793],[-65,2],[-37,-20],[-41,-63],[-73,-5],[-21,60],[-48,22],[-50,-14],[-42,-40],[-29,-51],[-43,112],[114,68],[64,24],[-5,100],[63,5],[-17,81],[55,31],[42,0],[89,24],[136,8],[42,-29],[78,-24],[63,-70],[28,10],[66,73],[-31,-128],[-6,-119],[47,-39],[-7,-72],[-37,0],[-70,28],[-112,-13]],[[1248,754],[-80,79],[-73,-40]],[[1248,754],[-46,-29],[25,-122],[-46,26],[-48,127],[-38,37]],[[3757,40],[-36,56],[24,34],[73,15],[26,-27],[37,-98],[-21,-20],[-103,40]],[[4056,155],[21,-64],[-23,-21],[-140,57],[-52,51],[59,39],[122,-25],[13,-37]],[[3025,568],[-9,-91],[-53,-58],[-27,-6],[-75,49],[-64,-55],[-72,31],[12,46],[70,97],[39,31],[104,12],[23,-33],[52,-23]],[[2512,609],[69,40],[38,6],[-32,-107],[-53,-61],[-82,-15],[-33,27],[93,110]],[[2780,580],[-57,-47],[-81,20],[-3,65],[50,20],[95,10],[-4,-68]],[[2118,292],[58,90],[103,85],[64,-10],[99,-34],[106,-16],[28,-40],[-134,-56],[-87,3],[-116,-20],[-8,-59],[-43,-36],[-62,20],[-8,73]],[[3228,913],[13,-54],[-46,-32],[-43,27],[-48,62],[-9,51],[51,30],[41,-26],[41,-58]],[[1436,643],[94,37],[93,89],[78,-32],[92,3],[82,-89],[54,-119],[35,-124],[-37,-58],[-66,-59],[-10,67],[-36,23],[-54,-24],[-78,-16],[-51,30],[33,37],[13,45],[-48,48],[-71,-2],[-56,46],[-90,13],[23,85]],[[4346,2324],[22,-68],[-23,-45],[-64,10],[-16,49],[47,55],[34,-1]]],"transform":{"scale":[0.0003624879674840276,0.0002477719316969694],"translate":[19.513344710867727,59.904353314755]},"objects":{"features":{"type":"GeometryCollection","geometries":[{"arcs":[[0]],"type":"Polygon","properties":{"iso_a2":"AX","iso_3166_2":"AX-X11~","type":"","type_en":"","name_en":"Lumparland","name":"Lumparland","featurecla":"Admin-1 states provinces"}},{"arcs":[[1]],"type":"Polygon","properties":{"iso_a2":"AX","iso_3166_2":"AX-X04~","type":"","type_en":"","name_en":"Eckerö","name":"Eckerö","featurecla":"Admin-1 states provinces"}},{"arcs":[[2]],"type":"Polygon","properties":{"iso_a2":"AX","iso_3166_2":"AX-X12~","type":"","type_en":"","name_en":"Vårdö","name":"Vårdö","featurecla":"Admin-1 states provinces"}},{"arcs":[[[3]],[[4]],[[5]]],"type":"MultiPolygon","properties":{"iso_a2":"AX","iso_3166_2":"AX-X14~","type":"","type_en":"","name_en":"Kumlinge","name":"Kumlinge","featurecla":"Admin-1 states provinces"}},{"arcs":[[6,7]],"type":"Polygon","properties":{"iso_a2":"AX","iso_3166_2":"AX-X02~","type":"","type_en":"","name_en":"Jomala","name":"Jomala","featurecla":"Admin-1 states provinces"}},{"arcs":[[8,-8]],"type":"Polygon","properties":{"iso_a2":"AX","iso_3166_2":"AX-X09~","type":"","type_en":"","name_en":"Mariehamn","name":"Mariehamn","featurecla":"Admin-1 states provinces"}},{"arcs":[[[9]],[[10]]],"type":"MultiPolygon","properties":{"iso_a2":"AX","iso_3166_2":"AX-X16~","type":"","type_en":"","name_en":"Kökar","name":"Kökar","featurecla":"Admin-1 states provinces"}},{"arcs":[[[11]],[[12]],[[13]],[[14]]],"type":"MultiPolygon","properties":{"iso_a2":"AX","iso_3166_2":"AX-X06~","type":"","type_en":"","name_en":"Föglö","name":"Föglö","featurecla":"Admin-1 states provinces"}},{"arcs":[[15]],"type":"Polygon","properties":{"iso_a2":"AX","iso_3166_2":"AX-X13~","type":"","type_en":"","name_en":"Sottunga","name":"Sottunga","featurecla":"Admin-1 states provinces"}},{"arcs":[[16]],"type":"Polygon","properties":{"iso_a2":"AX","iso_3166_2":"AX-X10~","type":"","type_en":"","name_en":"Lemland","name":"Lemland","featurecla":"Admin-1 states provinces"}},{"arcs":[[17]],"type":"Polygon","properties":{"iso_a2":"AX","iso_3166_2":"AX-X15~","type":"","type_en":"","name_en":"Brändö","name":"Brändö","featurecla":"Admin-1 states provinces"}}]}}}